ask_api/__init__.py
ask_api/ask_api.py
ask_api/base/__init__.py
ask_api/base/role.py
ask_api/base/session.py
ask_api/config/__init__.py
ask_api/config/askapi_config.py
ask_api/llm/__init__.py
ask_api/llm/base.py
ask_api/llm/llm_util.py
ask_api/llm/openai.py
ask_api/prompt/__init__.py
ask_api/prompt/basic.py
ask_api/util/__init__.py
ask_api/util/askapi_asyn.py
ask_api/util/askapi_inspect.py
ask_api/util/askapi_log.py
ask_api/util/askapi_util.py
ask_api-0.1.0.dist-info/LICENSE
ask_api-0.1.0.dist-info/METADATA
ask_api-0.1.0.dist-info/WHEEL
ask_api-0.1.0.dist-info/top_level.txt
ask_api-0.1.0.dist-info/RECORD
