Metadata-Version: 2.1
Name: ask-api
Version: 0.1.0
Home-page: https://github.com/yanqingmen/ask-api
Author: yanqingmen
License: Apache License 2.0
Requires-Python: >=3.7
License-File: LICENSE
Requires-Dist: openai
Requires-Dist: nest-asyncio
Requires-Dist: jupyter
